__init__.py
cli.py
git_tools/__init__.py
git_tools/formatter.py
git_tools/repository.py
git_tools/scanner.py
utils/__init__.py
utils/print.py
utils/validation.py
utils/version.py
gits_statuses-0.1.50.dist-info/METADATA
gits_statuses-0.1.50.dist-info/WHEEL
gits_statuses-0.1.50.dist-info/entry_points.txt
gits_statuses-0.1.50.dist-info/top_level.txt
gits_statuses-0.1.50.dist-info/RECORD
